{
  "region": {
    "서울특별시": [
      "강남구",
      "강동구",
      "강북구",
      "강서구",
      "관악구",
      "광진구",
      "구로구",
      "금천구",
      "노원구",
      "도봉구",
      "동대문구",
      "동작구",
      "마포구",
      "서대문구",
      "서초구",
      "성동구",
      "성북구",
      "송파구",
      "양천구",
      "영등포구",
      "용산구",
      "은평구",
      "종로구",
      "중구",
      "중랑구"
    ],
    "인천광역시": [
      "계양구",
      "남동구",
      "동구",
      "미추홀구",
      "부평구",
      "서구",
      "연수구",
      "중구"
    ],
    "부산광역시": [
      "강서구",
      "금정구",
      "남구",
      "동구",
      "동래구",
      "부산진구",
      "북구",
      "사상구",
      "사하구",
      "서구",
      "수영구",
      "연제구",
      "영도구",
      "중구",
      "해운대구"
    ],
    "대전광역시": ["대덕구", "동구", "서구", "유성구", "중구"],
    "대구광역시": [
      "남구",
      "달서구",
      "달서군",
      "동구",
      "북구",
      "서구",
      "수성구",
      "중구"
    ],
    "울산광역시": ["남구", "동구", "북구", "중구", "울주군"],
    "광주광역시": ["광산구", "남구", "동구", "북구", "서구"],
    "제주특별자치도": ["서귀포시", "제주시"],
    "세종특별자치시": ["세종특별자치시"],
    "경기도": [
      "고양시",
      "과천시",
      "광명시",
      "광주시",
      "구리시",
      "군포시",
      "김포시",
      "남양주시",
      "동두천시",
      "부천시",
      "성남시",
      "수원시",
      "시흥시",
      "안산시",
      "안성시",
      "안양시",
      "양주시",
      "여주시",
      "오산시",
      "용인시",
      "의왕시",
      "의정부시",
      "이천시",
      "파주시",
      "평택시",
      "포천시",
      "하남시",
      "화성시",
      "가평군",
      "양평군",
      "연천군"
    ],
    "강원도": [
      "강릉시",
      "동해시",
      "삼척시",
      "속초시",
      "원주시",
      "춘천시",
      "태백시",
      "고성군",
      "양구군",
      "양양군",
      "영월군",
      "인제군",
      "정선군",
      "철원군",
      "평창군",
      "홍천군",
      "화천군",
      "횡성군"
    ],
    "충청북도": [
      "제천시",
      "청주시",
      "충주시",
      "괴산군",
      "단양군",
      "보은군",
      "영동군",
      "옥천군",
      "음성군",
      "증평군",
      "진천군"
    ],
    "충청남도": [
      "계룡시",
      "공주시",
      "논산시",
      "당진시",
      "보령시",
      "서산시",
      "아산시",
      "천안시",
      "금산군",
      "부여군",
      "서천군",
      "예산군",
      "청양군",
      "태안군",
      "홍성군"
    ],
    "경상북도": [
      "경산시",
      "경주시",
      "구미시",
      "김천시",
      "문경시",
      "상주시",
      "안동시",
      "영주시",
      "영천시",
      "포항시",
      "고령군",
      "군위군",
      "봉화군",
      "성주군",
      "영덕군",
      "영양군",
      "예천군",
      "울릉군",
      "울진군",
      "의성군",
      "청도군",
      "청송군",
      "칠곡군"
    ],
    "경상남도": [
      "거제시",
      "김해시",
      "밀양시",
      "사천시",
      "양산시",
      "진주시",
      "창원시",
      "통영시",
      "거창군",
      "고성군",
      "남해군",
      "산청군",
      "의령군",
      "창녕군",
      "하동군",
      "함안군",
      "함양군",
      "합천군"
    ],
    "전라북도": [
      "군산시",
      "김제시",
      "남원시",
      "익산시",
      "전주시",
      "정읍시",
      "고창군",
      "무주군",
      "부안군",
      "순창군",
      "완주군",
      "임실군",
      "장수군",
      "진안군"
    ],
    "전라남도": [
      "광양시",
      "나주시",
      "목포시",
      "순천시",
      "여수시",
      "강진군",
      "고흥군",
      "곡성군",
      "구례군",
      "담양군",
      "무안군",
      "보성군",
      "신안군",
      "영광군",
      "영암군",
      "완도군",
      "장성군",
      "장흥군",
      "진도군",
      "함평군",
      "해남군",
      "화순군"
    ]
  },
  "applyUsers": [
    {
      "name": "홍길동1",
      "gender": "F",
      "applyDate": "2022-06-24",
      "birth": "2020-06-16",
      "region": { "city": "서울", "district": "강동구" },
      "phone": "010-399-674",
      "email": "test1@gmail.com",
      "transportation": ["버스", "지하철", "택시"],
      "isWinning": false
    },
    {
      "name": "홍길동2",
      "gender": "M",
      "applyDate": "2021-12-18",
      "birth": "2021-07-12",
      "region": { "city": "서울", "district": "강동구" },
      "phone": "010-454-8967",
      "email": "test2@gmail.com",
      "transportation": ["버스", "지하철"],
      "isWinning": true
    },
    {
      "name": "홍길동3",
      "gender": "F",
      "applyDate": "2022-05-12",
      "birth": "2022-01-01",
      "region": { "city": "서울", "district": "강동구" },
      "phone": "010-7805-4216",
      "email": "test3@gmail.com",
      "transportation": [
        "버스",
        "지하철",
        "택시",
        "KTX/기차",
        "도보",
        "자전거",
        "전동킥보드"
      ],
      "isWinning": false
    },
    {
      "name": "홍길동4",
      "gender": "M",
      "applyDate": "2022-01-04",
      "birth": "2021-03-20",
      "region": { "city": "서울", "district": "강동구" },
      "phone": "010-6936-6015",
      "email": "test4@gmail.com",
      "transportation": ["버스"],
      "isWinning": true
    },
    {
      "name": "홍길동5",
      "gender": "F",
      "applyDate": "2022-07-04",
      "birth": "2019-10-11",
      "region": { "city": "서울", "district": "강동구" },
      "phone": "010-3409-8399",
      "email": "test5@gmail.com",
      "transportation": ["버스"],
      "isWinning": false
    },
    {
      "name": "홍길동6",
      "gender": "M",
      "applyDate": "2022-01-26",
      "birth": "2022-04-04",
      "region": { "city": "서울", "district": "강동구" },
      "phone": "010-2553-5931",
      "email": "test6@gmail.com",
      "transportation": ["버스", "지하철"],
      "isWinning": true
    },
    {
      "name": "홍길동7",
      "gender": "F",
      "applyDate": "2021-12-16",
      "birth": "2022-07-09",
      "region": { "city": "서울", "district": "강동구" },
      "phone": "010-5500-1757",
      "email": "test7@gmail.com",
      "transportation": ["버스"],
      "isWinning": false
    },
    {
      "name": "홍길동8",
      "gender": "M",
      "applyDate": "2022-02-03",
      "birth": "2020-10-04",
      "region": { "city": "서울", "district": "강동구" },
      "phone": "010-9061-9082",
      "email": "test8@gmail.com",
      "transportation": ["버스", "지하철", "택시", "KTX/기차"],
      "isWinning": true
    },
    {
      "name": "홍길동9",
      "gender": "F",
      "applyDate": "2021-12-29",
      "birth": "2021-10-11",
      "region": { "city": "서울", "district": "강동구" },
      "phone": "010-9486-9714",
      "email": "test9@gmail.com",
      "transportation": [
        "버스",
        "지하철",
        "택시",
        "KTX/기차",
        "도보",
        "자전거"
      ],
      "isWinning": false
    },
    {
      "name": "홍길동10",
      "gender": "M",
      "applyDate": "2022-04-29",
      "birth": "2019-10-15",
      "region": { "city": "서울", "district": "강동구" },
      "phone": "010-8224-2280",
      "email": "test10@gmail.com",
      "transportation": [
        "버스",
        "지하철",
        "택시",
        "KTX/기차",
        "도보",
        "자전거"
      ],
      "isWinning": true
    },
    {
      "name": "홍길동11",
      "gender": "F",
      "applyDate": "2022-06-12",
      "birth": "2020-04-30",
      "region": { "city": "서울", "district": "강동구" },
      "phone": "010-9153-1394",
      "email": "test11@gmail.com",
      "transportation": ["버스", "지하철", "택시", "KTX/기차"],
      "isWinning": false
    },
    {
      "name": "홍길동12",
      "gender": "M",
      "applyDate": "2022-03-31",
      "birth": "2020-09-04",
      "region": { "city": "서울", "district": "강동구" },
      "phone": "010-4626-5045",
      "email": "test12@gmail.com",
      "transportation": ["버스", "지하철", "택시", "KTX/기차", "도보"],
      "isWinning": true
    },
    {
      "name": "홍길동13",
      "gender": "F",
      "applyDate": "2022-04-14",
      "birth": "2019-08-31",
      "region": { "city": "서울", "district": "강동구" },
      "phone": "010-8205-8498",
      "email": "test13@gmail.com",
      "transportation": ["버스"],
      "isWinning": false
    },
    {
      "name": "홍길동14",
      "gender": "M",
      "applyDate": "2022-04-03",
      "birth": "2020-12-11",
      "region": { "city": "서울", "district": "강동구" },
      "phone": "010-1478-2493",
      "email": "test14@gmail.com",
      "transportation": ["버스", "지하철", "택시", "KTX/기차", "도보"],
      "isWinning": true
    },
    {
      "name": "홍길동15",
      "gender": "F",
      "applyDate": "2022-07-14",
      "birth": "2021-04-10",
      "region": { "city": "서울", "district": "강동구" },
      "phone": "010-1578-5281",
      "email": "test15@gmail.com",
      "transportation": [
        "버스",
        "지하철",
        "택시",
        "KTX/기차",
        "도보",
        "자전거",
        "전동킥보드"
      ],
      "isWinning": false
    },
    {
      "name": "홍길동16",
      "gender": "M",
      "applyDate": "2021-12-15",
      "birth": "2022-06-09",
      "region": { "city": "서울", "district": "강동구" },
      "phone": "010-298-2948",
      "email": "test16@gmail.com",
      "transportation": ["버스", "지하철", "택시", "KTX/기차", "도보"],
      "isWinning": true
    },
    {
      "name": "홍길동17",
      "gender": "F",
      "applyDate": "2022-07-03",
      "birth": "2022-05-28",
      "region": { "city": "서울", "district": "강동구" },
      "phone": "010-8463-6936",
      "email": "test17@gmail.com",
      "transportation": ["버스", "지하철", "택시", "KTX/기차", "도보"],
      "isWinning": false
    },
    {
      "name": "홍길동18",
      "gender": "M",
      "applyDate": "2022-01-23",
      "birth": "2020-08-17",
      "region": { "city": "서울", "district": "강동구" },
      "phone": "010-2860-8055",
      "email": "test18@gmail.com",
      "transportation": [
        "버스",
        "지하철",
        "택시",
        "KTX/기차",
        "도보",
        "자전거"
      ],
      "isWinning": true
    },
    {
      "name": "홍길동19",
      "gender": "F",
      "applyDate": "2022-05-15",
      "birth": "2021-12-30",
      "region": { "city": "서울", "district": "강동구" },
      "phone": "010-6046-391",
      "email": "test19@gmail.com",
      "transportation": ["버스", "지하철"],
      "isWinning": false
    },
    {
      "name": "홍길동20",
      "gender": "M",
      "applyDate": "2022-02-20",
      "birth": "2020-05-01",
      "region": { "city": "서울", "district": "강동구" },
      "phone": "010-232-6041",
      "email": "test20@gmail.com",
      "transportation": [
        "버스",
        "지하철",
        "택시",
        "KTX/기차",
        "도보",
        "자전거"
      ],
      "isWinning": true
    },
    {
      "name": "홍길동21",
      "gender": "F",
      "applyDate": "2022-04-12",
      "birth": "2022-03-01",
      "region": { "city": "서울", "district": "강동구" },
      "phone": "010-889-5432",
      "email": "test21@gmail.com",
      "transportation": ["버스", "지하철", "택시", "KTX/기차"],
      "isWinning": false
    },
    {
      "name": "홍길동22",
      "gender": "M",
      "applyDate": "2022-05-07",
      "birth": "2022-03-04",
      "region": { "city": "서울", "district": "강동구" },
      "phone": "010-9089-5499",
      "email": "test22@gmail.com",
      "transportation": ["버스", "지하철"],
      "isWinning": true
    },
    {
      "name": "홍길동23",
      "gender": "F",
      "applyDate": "2022-06-05",
      "birth": "2019-11-04",
      "region": { "city": "서울", "district": "강동구" },
      "phone": "010-5670-7416",
      "email": "test23@gmail.com",
      "transportation": ["버스", "지하철", "택시", "KTX/기차", "도보"],
      "isWinning": false
    },
    {
      "name": "홍길동24",
      "gender": "M",
      "applyDate": "2022-06-19",
      "birth": "2021-03-03",
      "region": { "city": "서울", "district": "강동구" },
      "phone": "010-7453-7678",
      "email": "test24@gmail.com",
      "transportation": ["버스"],
      "isWinning": true
    },
    {
      "name": "홍길동25",
      "gender": "F",
      "applyDate": "2022-01-11",
      "birth": "2021-01-22",
      "region": { "city": "서울", "district": "강동구" },
      "phone": "010-3517-6308",
      "email": "test25@gmail.com",
      "transportation": ["버스"],
      "isWinning": false
    },
    {
      "name": "홍길동26",
      "gender": "M",
      "applyDate": "2022-05-04",
      "birth": "2020-07-29",
      "region": { "city": "서울", "district": "강동구" },
      "phone": "010-3667-1087",
      "email": "test26@gmail.com",
      "transportation": ["버스", "지하철", "택시", "KTX/기차"],
      "isWinning": true
    },
    {
      "name": "홍길동27",
      "gender": "F",
      "applyDate": "2022-04-10",
      "birth": "2019-10-28",
      "region": { "city": "서울", "district": "강동구" },
      "phone": "010-2772-1780",
      "email": "test27@gmail.com",
      "transportation": ["버스", "지하철", "택시", "KTX/기차", "도보"],
      "isWinning": false
    },
    {
      "name": "홍길동28",
      "gender": "M",
      "applyDate": "2022-07-11",
      "birth": "2022-07-13",
      "region": { "city": "서울", "district": "강동구" },
      "phone": "010-3336-4301",
      "email": "test28@gmail.com",
      "transportation": [
        "버스",
        "지하철",
        "택시",
        "KTX/기차",
        "도보",
        "자전거",
        "전동킥보드"
      ],
      "isWinning": true
    },
    {
      "name": "홍길동29",
      "gender": "F",
      "applyDate": "2022-02-17",
      "birth": "2019-12-13",
      "region": { "city": "서울", "district": "강동구" },
      "phone": "010-7478-9062",
      "email": "test29@gmail.com",
      "transportation": [
        "버스",
        "지하철",
        "택시",
        "KTX/기차",
        "도보",
        "자전거",
        "전동킥보드"
      ],
      "isWinning": false
    },
    {
      "name": "홍길동30",
      "gender": "M",
      "applyDate": "2022-04-12",
      "birth": "2019-12-11",
      "region": { "city": "서울", "district": "강동구" },
      "phone": "010-7947-8419",
      "email": "test30@gmail.com",
      "transportation": ["버스"],
      "isWinning": true
    },
    {
      "name": "홍길동31",
      "gender": "F",
      "applyDate": "2022-03-12",
      "birth": "2022-01-25",
      "region": { "city": "서울", "district": "강동구" },
      "phone": "010-87-7049",
      "email": "test31@gmail.com",
      "transportation": ["버스", "지하철", "택시", "KTX/기차", "도보"],
      "isWinning": false
    },
    {
      "name": "홍길동32",
      "gender": "M",
      "applyDate": "2022-05-09",
      "birth": "2020-05-17",
      "region": { "city": "서울", "district": "강동구" },
      "phone": "010-7965-5429",
      "email": "test32@gmail.com",
      "transportation": ["버스"],
      "isWinning": true
    },
    {
      "name": "홍길동33",
      "gender": "F",
      "applyDate": "2022-03-15",
      "birth": "2021-02-10",
      "region": { "city": "서울", "district": "강동구" },
      "phone": "010-8679-3726",
      "email": "test33@gmail.com",
      "transportation": ["버스", "지하철", "택시", "KTX/기차", "도보"],
      "isWinning": false
    },
    {
      "name": "홍길동34",
      "gender": "M",
      "applyDate": "2022-05-09",
      "birth": "2020-11-29",
      "region": { "city": "서울", "district": "강동구" },
      "phone": "010-9926-5261",
      "email": "test34@gmail.com",
      "transportation": ["버스", "지하철"],
      "isWinning": true
    },
    {
      "name": "홍길동35",
      "gender": "F",
      "applyDate": "2022-06-19",
      "birth": "2021-10-21",
      "region": { "city": "서울", "district": "강동구" },
      "phone": "010-1075-8215",
      "email": "test35@gmail.com",
      "transportation": ["버스", "지하철"],
      "isWinning": false
    },
    {
      "name": "홍길동36",
      "gender": "M",
      "applyDate": "2022-07-21",
      "birth": "2022-03-19",
      "region": { "city": "서울", "district": "강동구" },
      "phone": "010-3066-695",
      "email": "test36@gmail.com",
      "transportation": ["버스", "지하철", "택시", "KTX/기차", "도보"],
      "isWinning": true
    },
    {
      "name": "홍길동37",
      "gender": "F",
      "applyDate": "2022-05-27",
      "birth": "2019-06-09",
      "region": { "city": "서울", "district": "강동구" },
      "phone": "010-2882-3758",
      "email": "test37@gmail.com",
      "transportation": ["버스", "지하철", "택시", "KTX/기차"],
      "isWinning": false
    },
    {
      "name": "홍길동38",
      "gender": "M",
      "applyDate": "2022-06-10",
      "birth": "2019-07-20",
      "region": { "city": "서울", "district": "강동구" },
      "phone": "010-9836-3843",
      "email": "test38@gmail.com",
      "transportation": ["버스"],
      "isWinning": true
    },
    {
      "name": "홍길동39",
      "gender": "F",
      "applyDate": "2022-06-15",
      "birth": "2021-09-25",
      "region": { "city": "서울", "district": "강동구" },
      "phone": "010-4301-7070",
      "email": "test39@gmail.com",
      "transportation": ["버스", "지하철", "택시", "KTX/기차", "도보"],
      "isWinning": false
    },
    {
      "name": "홍길동40",
      "gender": "M",
      "applyDate": "2022-07-11",
      "birth": "2020-07-30",
      "region": { "city": "서울", "district": "강동구" },
      "phone": "010-2282-9512",
      "email": "test40@gmail.com",
      "transportation": ["버스"],
      "isWinning": true
    },
    {
      "name": "홍길동41",
      "gender": "F",
      "applyDate": "2022-03-25",
      "birth": "2020-10-30",
      "region": { "city": "서울", "district": "강동구" },
      "phone": "010-2497-2840",
      "email": "test41@gmail.com",
      "transportation": ["버스", "지하철", "택시"],
      "isWinning": false
    },
    {
      "name": "홍길동42",
      "gender": "M",
      "applyDate": "2022-05-07",
      "birth": "2022-03-06",
      "region": { "city": "서울", "district": "강동구" },
      "phone": "010-2968-6796",
      "email": "test42@gmail.com",
      "transportation": ["버스"],
      "isWinning": true
    },
    {
      "name": "홍길동43",
      "gender": "F",
      "applyDate": "2022-01-27",
      "birth": "2020-01-07",
      "region": { "city": "서울", "district": "강동구" },
      "phone": "010-68-7176",
      "email": "test43@gmail.com",
      "transportation": ["버스", "지하철", "택시", "KTX/기차"],
      "isWinning": false
    },
    {
      "name": "홍길동44",
      "gender": "M",
      "applyDate": "2022-07-23",
      "birth": "2020-03-17",
      "region": { "city": "서울", "district": "강동구" },
      "phone": "010-9356-6677",
      "email": "test44@gmail.com",
      "transportation": ["버스", "지하철", "택시"],
      "isWinning": true
    },
    {
      "name": "홍길동45",
      "gender": "F",
      "applyDate": "2021-12-31",
      "birth": "2020-03-21",
      "region": { "city": "서울", "district": "강동구" },
      "phone": "010-7658-4451",
      "email": "test45@gmail.com",
      "transportation": ["버스", "지하철", "택시", "KTX/기차"],
      "isWinning": false
    },
    {
      "name": "홍길동46",
      "gender": "M",
      "applyDate": "2022-03-25",
      "birth": "2022-07-15",
      "region": { "city": "서울", "district": "강동구" },
      "phone": "010-3482-2129",
      "email": "test46@gmail.com",
      "transportation": ["버스", "지하철", "택시", "KTX/기차", "도보"],
      "isWinning": true
    },
    {
      "name": "홍길동47",
      "gender": "F",
      "applyDate": "2022-03-02",
      "birth": "2022-03-16",
      "region": { "city": "서울", "district": "강동구" },
      "phone": "010-8684-9706",
      "email": "test47@gmail.com",
      "transportation": [
        "버스",
        "지하철",
        "택시",
        "KTX/기차",
        "도보",
        "자전거"
      ],
      "isWinning": false
    },
    {
      "name": "홍길동48",
      "gender": "M",
      "applyDate": "2022-05-15",
      "birth": "2019-12-08",
      "region": { "city": "서울", "district": "강동구" },
      "phone": "010-505-7672",
      "email": "test48@gmail.com",
      "transportation": ["버스", "지하철", "택시", "KTX/기차"],
      "isWinning": true
    },
    {
      "name": "홍길동49",
      "gender": "F",
      "applyDate": "2022-02-09",
      "birth": "2020-07-27",
      "region": { "city": "서울", "district": "강동구" },
      "phone": "010-3616-7520",
      "email": "test49@gmail.com",
      "transportation": ["버스"],
      "isWinning": false
    },
    {
      "name": "홍길동50",
      "gender": "M",
      "applyDate": "2022-01-21",
      "birth": "2021-06-23",
      "region": { "city": "서울", "district": "강동구" },
      "phone": "010-283-4642",
      "email": "test50@gmail.com",
      "transportation": ["버스", "지하철", "택시"],
      "isWinning": true
    },
    {
      "name": "홍길동51",
      "gender": "F",
      "applyDate": "2022-04-07",
      "birth": "2020-12-02",
      "region": { "city": "서울", "district": "강동구" },
      "phone": "010-2439-9858",
      "email": "test51@gmail.com",
      "transportation": ["버스"],
      "isWinning": false
    },
    {
      "name": "홍길동52",
      "gender": "M",
      "applyDate": "2022-07-09",
      "birth": "2021-01-05",
      "region": { "city": "서울", "district": "강동구" },
      "phone": "010-658-4574",
      "email": "test52@gmail.com",
      "transportation": ["버스", "지하철"],
      "isWinning": true
    },
    {
      "name": "홍길동53",
      "gender": "F",
      "applyDate": "2022-07-11",
      "birth": "2020-07-26",
      "region": { "city": "서울", "district": "강동구" },
      "phone": "010-9448-6601",
      "email": "test53@gmail.com",
      "transportation": ["버스"],
      "isWinning": false
    },
    {
      "name": "홍길동54",
      "gender": "M",
      "applyDate": "2022-02-09",
      "birth": "2021-05-21",
      "region": { "city": "서울", "district": "강동구" },
      "phone": "010-7106-5992",
      "email": "test54@gmail.com",
      "transportation": [
        "버스",
        "지하철",
        "택시",
        "KTX/기차",
        "도보",
        "자전거",
        "전동킥보드"
      ],
      "isWinning": true
    },
    {
      "name": "홍길동55",
      "gender": "F",
      "applyDate": "2022-01-22",
      "birth": "2020-03-31",
      "region": { "city": "서울", "district": "강동구" },
      "phone": "010-4316-3614",
      "email": "test55@gmail.com",
      "transportation": ["버스", "지하철"],
      "isWinning": false
    },
    {
      "name": "홍길동56",
      "gender": "M",
      "applyDate": "2022-02-12",
      "birth": "2020-11-16",
      "region": { "city": "서울", "district": "강동구" },
      "phone": "010-8594-9543",
      "email": "test56@gmail.com",
      "transportation": ["버스"],
      "isWinning": true
    },
    {
      "name": "홍길동57",
      "gender": "F",
      "applyDate": "2022-01-13",
      "birth": "2019-09-06",
      "region": { "city": "서울", "district": "강동구" },
      "phone": "010-5191-7879",
      "email": "test57@gmail.com",
      "transportation": ["버스"],
      "isWinning": false
    },
    {
      "name": "홍길동58",
      "gender": "M",
      "applyDate": "2022-03-23",
      "birth": "2021-09-24",
      "region": { "city": "서울", "district": "강동구" },
      "phone": "010-1881-538",
      "email": "test58@gmail.com",
      "transportation": ["버스", "지하철", "택시", "KTX/기차", "도보"],
      "isWinning": true
    },
    {
      "name": "홍길동59",
      "gender": "F",
      "applyDate": "2022-06-17",
      "birth": "2020-05-31",
      "region": { "city": "서울", "district": "강동구" },
      "phone": "010-3110-9504",
      "email": "test59@gmail.com",
      "transportation": ["버스"],
      "isWinning": false
    },
    {
      "name": "홍길동60",
      "gender": "M",
      "applyDate": "2021-12-08",
      "birth": "2020-02-05",
      "region": { "city": "서울", "district": "강동구" },
      "phone": "010-252-4681",
      "email": "test60@gmail.com",
      "transportation": ["버스", "지하철", "택시", "KTX/기차", "도보"],
      "isWinning": true
    },
    {
      "name": "홍길동61",
      "gender": "F",
      "applyDate": "2022-04-30",
      "birth": "2021-09-16",
      "region": { "city": "서울", "district": "강동구" },
      "phone": "010-4902-6877",
      "email": "test61@gmail.com",
      "transportation": [
        "버스",
        "지하철",
        "택시",
        "KTX/기차",
        "도보",
        "자전거",
        "전동킥보드"
      ],
      "isWinning": false
    },
    {
      "name": "홍길동62",
      "gender": "M",
      "applyDate": "2022-04-21",
      "birth": "2019-06-19",
      "region": { "city": "서울", "district": "강동구" },
      "phone": "010-3536-2709",
      "email": "test62@gmail.com",
      "transportation": [
        "버스",
        "지하철",
        "택시",
        "KTX/기차",
        "도보",
        "자전거",
        "전동킥보드"
      ],
      "isWinning": true
    },
    {
      "name": "홍길동63",
      "gender": "F",
      "applyDate": "2022-07-11",
      "birth": "2022-03-15",
      "region": { "city": "서울", "district": "강동구" },
      "phone": "010-3538-7110",
      "email": "test63@gmail.com",
      "transportation": [
        "버스",
        "지하철",
        "택시",
        "KTX/기차",
        "도보",
        "자전거"
      ],
      "isWinning": false
    },
    {
      "name": "홍길동64",
      "gender": "M",
      "applyDate": "2022-02-06",
      "birth": "2020-05-13",
      "region": { "city": "서울", "district": "강동구" },
      "phone": "010-7567-8747",
      "email": "test64@gmail.com",
      "transportation": [
        "버스",
        "지하철",
        "택시",
        "KTX/기차",
        "도보",
        "자전거",
        "전동킥보드"
      ],
      "isWinning": true
    },
    {
      "name": "홍길동65",
      "gender": "F",
      "applyDate": "2022-01-19",
      "birth": "2021-05-07",
      "region": { "city": "서울", "district": "강동구" },
      "phone": "010-7831-6083",
      "email": "test65@gmail.com",
      "transportation": [
        "버스",
        "지하철",
        "택시",
        "KTX/기차",
        "도보",
        "자전거"
      ],
      "isWinning": false
    },
    {
      "name": "홍길동66",
      "gender": "M",
      "applyDate": "2022-06-01",
      "birth": "2020-07-24",
      "region": { "city": "서울", "district": "강동구" },
      "phone": "010-4846-1998",
      "email": "test66@gmail.com",
      "transportation": ["버스"],
      "isWinning": true
    },
    {
      "name": "홍길동67",
      "gender": "F",
      "applyDate": "2022-06-01",
      "birth": "2021-09-08",
      "region": { "city": "서울", "district": "강동구" },
      "phone": "010-6455-5475",
      "email": "test67@gmail.com",
      "transportation": ["버스"],
      "isWinning": false
    },
    {
      "name": "홍길동68",
      "gender": "M",
      "applyDate": "2022-04-21",
      "birth": "2021-08-29",
      "region": { "city": "서울", "district": "강동구" },
      "phone": "010-8391-626",
      "email": "test68@gmail.com",
      "transportation": ["버스"],
      "isWinning": true
    },
    {
      "name": "홍길동69",
      "gender": "F",
      "applyDate": "2022-01-14",
      "birth": "2020-11-05",
      "region": { "city": "서울", "district": "강동구" },
      "phone": "010-6727-4210",
      "email": "test69@gmail.com",
      "transportation": ["버스", "지하철", "택시", "KTX/기차"],
      "isWinning": false
    },
    {
      "name": "홍길동70",
      "gender": "M",
      "applyDate": "2022-06-27",
      "birth": "2021-05-04",
      "region": { "city": "서울", "district": "강동구" },
      "phone": "010-7257-1990",
      "email": "test70@gmail.com",
      "transportation": [
        "버스",
        "지하철",
        "택시",
        "KTX/기차",
        "도보",
        "자전거",
        "전동킥보드"
      ],
      "isWinning": true
    },
    {
      "name": "홍길동71",
      "gender": "F",
      "applyDate": "2022-04-07",
      "birth": "2021-07-13",
      "region": { "city": "서울", "district": "강동구" },
      "phone": "010-5220-7057",
      "email": "test71@gmail.com",
      "transportation": ["버스", "지하철", "택시", "KTX/기차"],
      "isWinning": false
    },
    {
      "name": "홍길동72",
      "gender": "M",
      "applyDate": "2022-07-21",
      "birth": "2021-02-07",
      "region": { "city": "서울", "district": "강동구" },
      "phone": "010-6982-856",
      "email": "test72@gmail.com",
      "transportation": ["버스", "지하철", "택시"],
      "isWinning": true
    },
    {
      "name": "홍길동73",
      "gender": "F",
      "applyDate": "2022-05-24",
      "birth": "2020-06-22",
      "region": { "city": "서울", "district": "강동구" },
      "phone": "010-144-3760",
      "email": "test73@gmail.com",
      "transportation": [
        "버스",
        "지하철",
        "택시",
        "KTX/기차",
        "도보",
        "자전거"
      ],
      "isWinning": false
    },
    {
      "name": "홍길동74",
      "gender": "M",
      "applyDate": "2022-02-13",
      "birth": "2022-01-31",
      "region": { "city": "서울", "district": "강동구" },
      "phone": "010-6490-7683",
      "email": "test74@gmail.com",
      "transportation": ["버스"],
      "isWinning": true
    },
    {
      "name": "홍길동75",
      "gender": "F",
      "applyDate": "2022-07-13",
      "birth": "2021-03-15",
      "region": { "city": "서울", "district": "강동구" },
      "phone": "010-3729-9237",
      "email": "test75@gmail.com",
      "transportation": ["버스"],
      "isWinning": false
    },
    {
      "name": "홍길동76",
      "gender": "M",
      "applyDate": "2022-05-09",
      "birth": "2019-11-05",
      "region": { "city": "서울", "district": "강동구" },
      "phone": "010-5218-8840",
      "email": "test76@gmail.com",
      "transportation": ["버스", "지하철"],
      "isWinning": true
    },
    {
      "name": "홍길동77",
      "gender": "F",
      "applyDate": "2022-03-05",
      "birth": "2021-06-11",
      "region": { "city": "서울", "district": "강동구" },
      "phone": "010-9531-8927",
      "email": "test77@gmail.com",
      "transportation": [
        "버스",
        "지하철",
        "택시",
        "KTX/기차",
        "도보",
        "자전거",
        "전동킥보드"
      ],
      "isWinning": false
    },
    {
      "name": "홍길동78",
      "gender": "M",
      "applyDate": "2022-07-09",
      "birth": "2020-02-10",
      "region": { "city": "서울", "district": "강동구" },
      "phone": "010-3713-4834",
      "email": "test78@gmail.com",
      "transportation": ["버스", "지하철", "택시", "KTX/기차", "도보"],
      "isWinning": true
    },
    {
      "name": "홍길동79",
      "gender": "F",
      "applyDate": "2021-12-14",
      "birth": "2022-03-20",
      "region": { "city": "서울", "district": "강동구" },
      "phone": "010-7480-8166",
      "email": "test79@gmail.com",
      "transportation": [
        "버스",
        "지하철",
        "택시",
        "KTX/기차",
        "도보",
        "자전거"
      ],
      "isWinning": false
    },
    {
      "name": "홍길동80",
      "gender": "M",
      "applyDate": "2022-03-25",
      "birth": "2022-05-24",
      "region": { "city": "서울", "district": "강동구" },
      "phone": "010-5458-3049",
      "email": "test80@gmail.com",
      "transportation": ["버스", "지하철", "택시"],
      "isWinning": true
    },
    {
      "name": "홍길동81",
      "gender": "F",
      "applyDate": "2022-02-28",
      "birth": "2021-06-19",
      "region": { "city": "서울", "district": "강동구" },
      "phone": "010-9926-4799",
      "email": "test81@gmail.com",
      "transportation": ["버스", "지하철", "택시", "KTX/기차", "도보"],
      "isWinning": false
    },
    {
      "name": "홍길동82",
      "gender": "M",
      "applyDate": "2022-01-29",
      "birth": "2022-01-25",
      "region": { "city": "서울", "district": "강동구" },
      "phone": "010-3333-5851",
      "email": "test82@gmail.com",
      "transportation": [
        "버스",
        "지하철",
        "택시",
        "KTX/기차",
        "도보",
        "자전거",
        "전동킥보드"
      ],
      "isWinning": true
    },
    {
      "name": "홍길동83",
      "gender": "F",
      "applyDate": "2022-05-26",
      "birth": "2019-09-25",
      "region": { "city": "서울", "district": "강동구" },
      "phone": "010-8554-4548",
      "email": "test83@gmail.com",
      "transportation": [
        "버스",
        "지하철",
        "택시",
        "KTX/기차",
        "도보",
        "자전거",
        "전동킥보드"
      ],
      "isWinning": false
    },
    {
      "name": "홍길동84",
      "gender": "M",
      "applyDate": "2022-04-04",
      "birth": "2020-02-12",
      "region": { "city": "서울", "district": "강동구" },
      "phone": "010-6310-8505",
      "email": "test84@gmail.com",
      "transportation": ["버스"],
      "isWinning": true
    },
    {
      "name": "홍길동85",
      "gender": "F",
      "applyDate": "2022-07-17",
      "birth": "2020-07-13",
      "region": { "city": "서울", "district": "강동구" },
      "phone": "010-5666-8938",
      "email": "test85@gmail.com",
      "transportation": ["버스", "지하철", "택시", "KTX/기차"],
      "isWinning": false
    },
    {
      "name": "홍길동86",
      "gender": "M",
      "applyDate": "2022-07-18",
      "birth": "2020-09-11",
      "region": { "city": "서울", "district": "강동구" },
      "phone": "010-5848-7351",
      "email": "test86@gmail.com",
      "transportation": [
        "버스",
        "지하철",
        "택시",
        "KTX/기차",
        "도보",
        "자전거",
        "전동킥보드"
      ],
      "isWinning": true
    },
    {
      "name": "홍길동87",
      "gender": "F",
      "applyDate": "2022-02-21",
      "birth": "2021-05-26",
      "region": { "city": "서울", "district": "강동구" },
      "phone": "010-2263-466",
      "email": "test87@gmail.com",
      "transportation": ["버스", "지하철"],
      "isWinning": false
    },
    {
      "name": "홍길동88",
      "gender": "M",
      "applyDate": "2022-03-31",
      "birth": "2021-06-07",
      "region": { "city": "서울", "district": "강동구" },
      "phone": "010-7956-6520",
      "email": "test88@gmail.com",
      "transportation": [
        "버스",
        "지하철",
        "택시",
        "KTX/기차",
        "도보",
        "자전거",
        "전동킥보드"
      ],
      "isWinning": true
    },
    {
      "name": "홍길동89",
      "gender": "F",
      "applyDate": "2022-01-18",
      "birth": "2019-06-24",
      "region": { "city": "서울", "district": "강동구" },
      "phone": "010-9399-6803",
      "email": "test89@gmail.com",
      "transportation": ["버스"],
      "isWinning": false
    },
    {
      "name": "홍길동90",
      "gender": "M",
      "applyDate": "2022-03-05",
      "birth": "2022-04-25",
      "region": { "city": "서울", "district": "강동구" },
      "phone": "010-6010-1917",
      "email": "test90@gmail.com",
      "transportation": [
        "버스",
        "지하철",
        "택시",
        "KTX/기차",
        "도보",
        "자전거"
      ],
      "isWinning": true
    },
    {
      "name": "홍길동91",
      "gender": "F",
      "applyDate": "2022-03-03",
      "birth": "2020-01-26",
      "region": { "city": "서울", "district": "강동구" },
      "phone": "010-7480-3208",
      "email": "test91@gmail.com",
      "transportation": ["버스", "지하철", "택시", "KTX/기차", "도보"],
      "isWinning": false
    },
    {
      "name": "홍길동92",
      "gender": "M",
      "applyDate": "2021-12-08",
      "birth": "2021-09-03",
      "region": { "city": "서울", "district": "강동구" },
      "phone": "010-4730-281",
      "email": "test92@gmail.com",
      "transportation": ["버스"],
      "isWinning": true
    },
    {
      "name": "홍길동93",
      "gender": "F",
      "applyDate": "2022-04-28",
      "birth": "2020-03-14",
      "region": { "city": "서울", "district": "강동구" },
      "phone": "010-1214-8495",
      "email": "test93@gmail.com",
      "transportation": [
        "버스",
        "지하철",
        "택시",
        "KTX/기차",
        "도보",
        "자전거",
        "전동킥보드"
      ],
      "isWinning": false
    },
    {
      "name": "홍길동94",
      "gender": "M",
      "applyDate": "2022-01-06",
      "birth": "2019-08-16",
      "region": { "city": "서울", "district": "강동구" },
      "phone": "010-9652-6678",
      "email": "test94@gmail.com",
      "transportation": [
        "버스",
        "지하철",
        "택시",
        "KTX/기차",
        "도보",
        "자전거"
      ],
      "isWinning": true
    },
    {
      "name": "홍길동95",
      "gender": "F",
      "applyDate": "2022-05-20",
      "birth": "2021-05-21",
      "region": { "city": "서울", "district": "강동구" },
      "phone": "010-3131-9539",
      "email": "test95@gmail.com",
      "transportation": ["버스", "지하철"],
      "isWinning": false
    },
    {
      "name": "홍길동96",
      "gender": "M",
      "applyDate": "2022-05-09",
      "birth": "2021-07-09",
      "region": { "city": "서울", "district": "강동구" },
      "phone": "010-2467-7458",
      "email": "test96@gmail.com",
      "transportation": ["버스", "지하철", "택시", "KTX/기차", "도보"],
      "isWinning": true
    },
    {
      "name": "홍길동97",
      "gender": "F",
      "applyDate": "2022-04-05",
      "birth": "2019-08-16",
      "region": { "city": "서울", "district": "강동구" },
      "phone": "010-5127-4541",
      "email": "test97@gmail.com",
      "transportation": [
        "버스",
        "지하철",
        "택시",
        "KTX/기차",
        "도보",
        "자전거"
      ],
      "isWinning": false
    },
    {
      "name": "홍길동98",
      "gender": "M",
      "applyDate": "2022-01-21",
      "birth": "2020-04-24",
      "region": { "city": "서울", "district": "강동구" },
      "phone": "010-2465-2873",
      "email": "test98@gmail.com",
      "transportation": ["버스"],
      "isWinning": true
    },
    {
      "name": "홍길동99",
      "gender": "F",
      "applyDate": "2022-06-16",
      "birth": "2022-01-23",
      "region": { "city": "서울", "district": "강동구" },
      "phone": "010-2070-1313",
      "email": "test99@gmail.com",
      "transportation": ["버스", "지하철"],
      "isWinning": false
    },
    {
      "name": "홍길동100",
      "gender": "M",
      "applyDate": "2021-12-20",
      "birth": "2020-05-10",
      "region": { "city": "서울", "district": "강동구" },
      "phone": "010-5389-4458",
      "email": "test100@gmail.com",
      "transportation": [
        "버스",
        "지하철",
        "택시",
        "KTX/기차",
        "도보",
        "자전거",
        "전동킥보드"
      ],
      "isWinning": true
    }
  ]
}
